{
  "tool": "circt",
  "issue_number": 6961,
  "title": "[FIRRTL][ExportVerilog] Signed Division Bug",
  "features": [
    {
      "name": "signed division with sign-extended operands via concatenation",
      "category": "data_model",
      "description": "Code should include a signed division where both operands are sign-extended via concatenation and cast with $signed()",
      "snippet": "$signed({a[2], a}) / $signed({b[2], b})",
      "tags": ["signed_division", "sign_extension", "concatenation", "$signed"],
      "source_bug_id": "circt-6961",
      "tool": "circt",
      "issue_url": "https://github.com/llvm/circt/issues/6961",
      "construct_complexity": 2,
      "ub_type": null,
      "error_pattern": "wrong_output"
    },
    {
      "name": "signed division result in zero-extended context",
      "category": "data_model",
      "description": "Code should include a signed division result used in a concatenation that zero-extends the result",
      "snippet": "{1'h0, $signed({a[2], a}) / $signed({b[2], b})}",
      "tags": ["signed_division", "zero_extension", "concatenation", "context_sensitivity"],
      "source_bug_id": "circt-6961",
      "tool": "circt",
      "issue_url": "https://github.com/llvm/circt/issues/6961",
      "construct_complexity": 2,
      "ub_type": null,
      "error_pattern": "wrong_output"
    },
    {
      "name": "signed division inlined into addition expression",
      "category": "control_flow",
      "description": "Code should include a signed division expression inlined into an addition expression, where the division result is part of a larger concatenation",
      "snippet": "assign d = {2'h0, c} + {1'h0, $signed({a[2], a}) / $signed({b[2], b})};",
      "tags": ["signed_division", "addition", "concatenation", "inlining", "context_sensitivity"],
      "source_bug_id": "circt-6961",
      "tool": "circt",
      "issue_url": "https://github.com/llvm/circt/issues/6961",
      "construct_complexity": 3,
      "ub_type": null,
      "error_pattern": "wrong_output"
    }
  ],
  "extraction_summary": {
    "code_blocks_found": 0,
    "features_extracted": 3,
    "features_after_dedup": 3
  }
}
