{
  "tool": "verilator",
  "type": "pull_request",
  "issue_number": 6967,
  "issue_url": "https://github.com/verilator/verilator/pull/6967",
  "title": "Fix UNUSED / UNDRIVEN for unused functions (#6893)",
  "body": "Variables in unused functions toss very confusing warnings:\r\n```\r\nunc/vlt_compile.log                                                                                                                                                                                                                                                                                                                                                                                                                      %Warning-UNUSEDSIGNAL: t/t_unused_func.v:7:33: Signal is not used: 'val'                                                                                                                                                                                                                                                                                                                                                                 \r\n                                             : ... note: In instance 't'                                                                                                                                                                                                                                                                                                                                                                     7 | function automatic int foo(real val);                                                                                                                                                                                                                                                                                                                                                                                            \r\n      |                                 ^~~                                                                                                                                                                                                                                                                                                                                                                                              \r\n                       ... For warning description see https://verilator.org/warn/UNUSEDSIGNAL?v=5.045                                                                                                                                                                                                                                                                                                                                                          ... Use \"/* verilator lint_off UNUSEDSIGNAL */\" and lint_on around source to disable this message.                                                                                                                                                                                                                                                                                                                \r\n%Warning-UNUSEDSIGNAL: t/t_unused_func.v:8:7: Bits of signal are not driven, nor used: 'result'[31:1]                                                                                                               \r\n                                            : ... note: In instance 't'                                                                                                                                             \r\n    8 |   int result = $rtoi(val);                                                                                                                                                                                  \r\n      |       ^~~~~~                                                                                                                                                                                                \r\n%Warning-UNDRIVEN: t/t_unused_func.v:8:7: Bits of signal are not driven: 'result'[0]                                                                                                                                \r\n                                        : ... note: In instance 't'                                                                                                                                                 \r\n    8 |   int result = $rtoi(val);                                                                      \r\n      |       ^~~~~~                                                                                   \r\n                   ... For warning description see https://verilator.org/warn/UNDRIVEN?v=5.045         \r\n                   ... Use \"/* verilator lint_off UNDRIVEN */\" and lint_on around source to disable this message.\r\n%Warning-UNUSEDSIGNAL: t/t_unused_func.v:9:7: Signal is not driven, nor used: 'huh'                                                                                                                                                                                                                                                                                                                                                      \r\n                                            : ... note: In instance 't'                              \r\n    9 |   bit huh = result[0];                                                                                                                                                                                                                                                                                                                                                                                                           \r\n      |       ^~~                                                                                                                                                                                                                                                                                                                                                                                                                        \r\n```\r\n\r\nE.g. `val` is definitely used on line 8, but because the function isn't called, V3Undriven ripples through the func and yells about everything.  I guess there's an argument that you shouldn't have un-called functions and that instead the warnings should just be changed to say that instead.  However, I don't think that's a good plan since that discourages sharing functions via packages or included files (not everyone will use all the funcs).\r\n\r\nThis PR now marks Vars as driven / used in the function declaration.  That caused spurious MULTIDRIVEN warnings as was mentioned in the comment I changed.  So now you don't get MULTIDRIVEN if you're looking at a function declaration or if the last driver was the function declaration.",
  "labels": [],
  "state": "closed",
  "created_at": "2026-01-30",
  "closed_at": "2026-02-12",
  "code_blocks": [
    "unc/vlt_compile.log                                                                                                                                                                                                                                                                                                                                                                                                                      %Warning-UNUSEDSIGNAL: t/t_unused_func.v:7:33: Signal is not used: 'val'                                                                                                                                                                                                                                                                                                                                                                 \r\n                                             : ... note: In instance 't'                                                                                                                                                                                                                                                                                                                                                                     7 | function automatic int foo(real val);                                                                                                                                                                                                                                                                                                                                                                                            \r\n      |                                 ^~~                                                                                                                                                                                                                                                                                                                                                                                              \r\n                       ... For warning description see https://verilator.org/warn/UNUSEDSIGNAL?v=5.045                                                                                                                                                                                                                                                                                                                                                          ... Use \"/* verilator lint_off UNUSEDSIGNAL */\" and lint_on around source to disable this message.                                                                                                                                                                                                                                                                                                                \r\n%Warning-UNUSEDSIGNAL: t/t_unused_func.v:8:7: Bits of signal are not driven, nor used: 'result'[31:1]                                                                                                               \r\n                                            : ... note: In instance 't'                                                                                                                                             \r\n    8 |   int result = $rtoi(val);                                                                                                                                                                                  \r\n      |       ^~~~~~                                                                                                                                                                                                \r\n%Warning-UNDRIVEN: t/t_unused_func.v:8:7: Bits of signal are not driven: 'result'[0]                                                                                                                                \r\n                                        : ... note: In instance 't'                                                                                                                                                 \r\n    8 |   int result = $rtoi(val);                                                                      \r\n      |       ^~~~~~                                                                                   \r\n                   ... For warning description see https://verilator.org/warn/UNDRIVEN?v=5.045         \r\n                   ... Use \"/* verilator lint_off UNDRIVEN */\" and lint_on around source to disable this message.\r\n%Warning-UNUSEDSIGNAL: t/t_unused_func.v:9:7: Signal is not driven, nor used: 'huh'                                                                                                                                                                                                                                                                                                                                                      \r\n                                            : ... note: In instance 't'                              \r\n    9 |   bit huh = result[0];                                                                                                                                                                                                                                                                                                                                                                                                           \r\n      |       ^~~"
  ],
  "linked_pr": null,
  "pr_files": null,
  "pr_test_files": null
}
