{
  "tool": "circt",
  "issue_number": 10058,
  "title": "[circt-reduce] Add convention attribute remover",
  "features": [
    {
      "name": "FIRRTL module with convention attribute",
      "category": "data_model",
      "description": "Code should include a FIRRTL module or external module that carries an explicit convention attribute such as Scalarized or Internal",
      "snippet": "firrtl.module @Top(in %a: !firrtl.uint<1>) attributes {convention = #firrtl<convention scalarized>} {\n  firrtl.node %a : !firrtl.uint<1>\n}",
      "tags": [
        "firrtl",
        "module",
        "convention",
        "attribute",
        "mlir"
      ],
      "source_bug_id": "10058",
      "tool": "circt",
      "issue_url": "https://github.com/llvm/circt/pull/10058",
      "construct_complexity": 2,
      "ub_type": null
    },
    {
      "name": "FIRRTL external module with convention attribute",
      "category": "data_model",
      "description": "Code should include a FIRRTL external module declaration that carries an explicit convention attribute",
      "snippet": "firrtl.extmodule private @Ext(in a: !firrtl.uint<1>) attributes {convention = #firrtl<convention scalarized>}",
      "tags": [
        "firrtl",
        "extmodule",
        "convention",
        "attribute",
        "mlir"
      ],
      "source_bug_id": "10058",
      "tool": "circt",
      "issue_url": "https://github.com/llvm/circt/pull/10058",
      "construct_complexity": 2,
      "ub_type": null
    },
    {
      "name": "Default internal convention as absent attribute",
      "category": "data_model",
      "description": "Code should include a FIRRTL module that relies on the default internal convention by omitting the convention attribute entirely",
      "snippet": "firrtl.module @Top(in %a: !firrtl.uint<1>) {\n  firrtl.node %a : !firrtl.uint<1>\n}",
      "tags": [
        "firrtl",
        "module",
        "convention",
        "default",
        "internal",
        "mlir"
      ],
      "source_bug_id": "10058",
      "tool": "circt",
      "issue_url": "https://github.com/llvm/circt/pull/10058",
      "construct_complexity": 1,
      "ub_type": null
    }
  ],
  "extraction_summary": {
    "code_blocks_found": 0,
    "features_extracted": 3,
    "features_after_dedup": 3
  }
}