{
  "tool": "verilator",
  "type": "issue",
  "issue_number": 1414,
  "issue_url": "https://github.com/verilator/verilator/issues/1414",
  "title": "Multi dimensional variable in function causing issues",
  "body": "---\n\n\nAuthor Name: **Johan Wouters**\nOriginal Redmine Issue: 1414 from https://www.veripool.org\n\n\n\n---\n\nHi,\r\n\r\nI added a small example of a structure that causes issues in our codebase. We use a function to calculate a localparam and Verilator seems to fail because the function contains a multi-dimensional variable.\r\n\r\nThe message I get is:\r\n%Error: test.v:19: Expecting expression to be constant, but can't determine constant for FUNCREF 'problematic function'\r\n%Error: test.v:13 ... Location of non-constant ASSIGN: LHS isn't simple variable\r\n\r\n\r\nthis is with Verilator 4.012 and swithes -sv -Wno-lint -cc test.v --top-module test\r\n\r\nThe code can be simulated, logic synthesis and logic equivalence checking also works fine\n\n\n",
  "labels": [
    "resolution: duplicate"
  ],
  "state": "closed",
  "created_at": "2019-04-03",
  "closed_at": "2019-06-15",
  "code_blocks": [],
  "linked_pr": null,
  "pr_files": null,
  "pr_test_files": null
}
