{
  "tool": "circt",
  "issue_number": 2962,
  "title": "[ExportVerilog] Unnecessary temporary wires for single use values",
  "features": [
    {
      "name": "single_use_wire_inlining_in_always_ifdef",
      "category": "data_model",
      "description": "Code should include a wire assignment to an expression that is only used once, within an sv.always block containing an sv.ifdef block",
      "snippet": "wire _GEN = opcode == 3'h6;\nalways @(posedge clock) begin\n  `ifndef SYNTHESIS\n    if (_GEN) $error(\"Foo\");\n  `endif\nend",
      "tags": ["wire", "single_use", "inlining", "sv_always", "sv_ifdef"],
      "source_bug_id": "circt-2962",
      "tool": "circt",
      "issue_url": "https://github.com/llvm/circt/issues/2962",
      "construct_complexity": 2,
      "ub_type": null,
      "error_pattern": "wrong_output"
    },
    {
      "name": "comparison_in_if_condition_within_always_ifdef",
      "category": "control_flow",
      "description": "Code should include a comb.icmp result used in an if condition inside sv.always and sv.ifdef blocks",
      "snippet": "hw.constant -2 : i3\n%0 = comb.icmp eq %opcode, %c-2_i3 : i3\nsv.ifdef \"SYNTHESIS\" { } else {\n  sv.always posedge %clock {\n    sv.if %0 { sv.error \"Foo\" }\n  }\n}",
      "tags": ["comb_icmp", "sv_if", "sv_always", "sv_ifdef", "if_condition"],
      "source_bug_id": "circt-2962",
      "tool": "circt",
      "issue_url": "https://github.com/llvm/circt/issues/2962",
      "construct_complexity": 2,
      "ub_type": null,
      "error_pattern": "wrong_output"
    }
  ],
  "extraction_summary": {
    "code_blocks_found": 2,
    "features_extracted": 2,
    "features_after_dedup": 2
  }
}
