{
  "tool": "verilator",
  "issue_number": 7287,
  "title": "Fix streaming with descending unpacked arrays and unpacked-to-queue",
  "features": [
    {
      "name": "streaming to descending-range unpacked array",
      "category": "data_model",
      "description": "Code should include streaming assignment to a descending-range unpacked array where indices decrease (e.g., [3:0])",
      "snippet": "logic [3:0][7:0] packed_din;\nlogic [7:0] unpacked_des_dout[3:0];\nalways_comb {>>{unpacked_des_dout}} = packed_din;",
      "tags": [
        "streaming",
        "descending_range",
        "unpacked_array"
      ],
      "source_bug_id": "7287",
      "tool": "verilator",
      "issue_url": "https://github.com/verilator/verilator/pull/7287",
      "construct_complexity": 2,
      "ub_type": null,
      "error_pattern": "wrong_output"
    },
    {
      "name": "streaming unpacked array to queue",
      "category": "data_model",
      "description": "Code should include streaming assignment from an unpacked array to a queue using the streaming operator",
      "snippet": "logic [7:0] unpacked_din[4];\nlogic [7:0] queue_dout[$];\nalways_comb {>>{queue_dout}} = unpacked_din;",
      "tags": [
        "streaming",
        "unpacked_array",
        "queue"
      ],
      "source_bug_id": "7287",
      "tool": "verilator",
      "issue_url": "https://github.com/verilator/verilator/pull/7287",
      "construct_complexity": 2,
      "ub_type": null,
      "error_pattern": "wrong_output"
    }
  ]
}
