{
  "tool": "yosys",
  "type": "issue",
  "issue_number": 1762,
  "issue_url": "https://github.com/YosysHQ/yosys/issues/1762",
  "title": "No warning or error message when `add` command operates on bogus selection",
  "body": "## Steps to reproduce the issue\r\n\r\n```\r\nread_verilog /path/to/yosys/examples/igloo2/example.v\r\nadd -wire foo 1 opksadl sda90sd\r\nselect -list\r\n```\r\n\r\n## Expected behavior\r\n\r\nThe `add` command *should* either warn or generate an error about one or more of the following:\r\n1) 'opksadl' and 'sda90sd' are not valid object names\r\n2) attempting to add something to an empty selection\r\n3) command was `-wire` but ultimately no wires were added\r\n\r\n## Actual behavior\r\n\r\nNo such warnings or errors are generated.  Instead, nothing happens.  The selection is not changed, no wire is added, and nothing is printed to the console.\r\n",
  "labels": [],
  "state": "closed",
  "created_at": "2020-03-11",
  "closed_at": "2020-03-23",
  "code_blocks": [
    "read_verilog /path/to/yosys/examples/igloo2/example.v\r\nadd -wire foo 1 opksadl sda90sd\r\nselect -list"
  ],
  "linked_pr": null,
  "pr_files": null,
  "pr_test_files": null
}
