{
  "tool": "verilator",
  "issue_number": 738,
  "title": "AstReplicate constructor consistency",
  "features": [
    {
      "name": "replication operator with width calculation",
      "category": "data_model",
      "description": "Code should include a replication expression with constant repeat count where the result width equals operand width multiplied by repeat count",
      "snippet": "logic [7:0] a;\nlogic [15:0] b = {2{a}};",
      "tags": ["replication", "width_calculation", "constant_repeat"],
      "source_bug_id": "738",
      "tool": "verilator",
      "issue_url": "https://github.com/verilator/verilator/issues/738",
      "construct_complexity": 2,
      "ub_type": null,
      "error_pattern": "wrong_output"
    }
  ],
  "extraction_summary": {
    "code_blocks_found": 1,
    "features_extracted": 1,
    "features_after_dedup": 1
  }
}