{
  "tool": "yosys",
  "issue_number": 3043,
  "title": "Remove unused wire in procedural for initialization",
  "features": [
    {
      "name": "for_loop_initialization_in_always_comb_causing_latch",
      "category": "timing",
      "description": "Code should include a for-loop with initialization declaring loop variables, placed inside an always_comb block with conditional logic that causes latch inference for the auto-generated implicit wire",
      "snippet": "always_comb begin\nif (cond) begin\nfor (int i = 0; i < N; i++) begin\n// loop body with if statement causes latch inference\nend\nend\nend",
      "tags": ["for_loop", "always_comb", "latch_inference", "implicit_wire"],
      "source_bug_id": "yosys-3043",
      "tool": "yosys",
      "issue_url": "https://github.com/YosysHQ/yosys/pull/3043",
      "construct_complexity": 2,
      "ub_type": null,
      "error_pattern": "wrong_output"
    }
  ],
  "extraction_summary": {
    "code_blocks_found": 0,
    "features_extracted": 1,
    "features_after_dedup": 1
  }
}
