{
  "tool": "yosys",
  "issue_number": 1482,
  "title": "Optimisations in OPT_LUT pass",
  "features": [
    {
      "name": "conditional_with_zero_alternative_in_arithmetic",
      "category": "data_model",
      "description": "Code should include a conditional expression with a zero alternative used as an operand in an arithmetic addition operation",
      "snippet": "z <= x + (s ? y : 0);",
      "tags": ["ternary", "conditional_operator", "arithmetic", "optimization"],
      "source_bug_id": "yosys-1482",
      "tool": "yosys",
      "issue_url": "https://github.com/YosysHQ/yosys/issues/1482",
      "construct_complexity": 2,
      "ub_type": null,
      "error_pattern": "wrong_output"
    },
    {
      "name": "equivalent_restructure_candidate",
      "category": "data_model",
      "description": "Code should include a conditional expression where the else branch is zero and the true branch performs addition, representing a restructure candidate that Yosys should optimize equivalently",
      "snippet": "z <= s ? (x + y) : x;",
      "tags": ["ternary", "conditional_operator", "arithmetic", "restructure"],
      "source_bug_id": "yosys-1482",
      "tool": "yosys",
      "issue_url": "https://github.com/YosysHQ/yosys/issues/1482",
      "construct_complexity": 2,
      "ub_type": null,
      "error_pattern": "wrong_output"
    },
    {
      "name": "mux_with_zero_operand",
      "category": "data_model",
      "description": "Code should include a multiplexer construct where one operand is zero, which should be optimizable to a conditional addition or subtraction",
      "snippet": "logic [3:0] mux_out;\nassign mux_out = s ? y : 4'b0;",
      "tags": ["mux", "zero_operand", "conditional", "optimization"],
      "source_bug_id": "yosys-1482",
      "tool": "yosys",
      "issue_url": "https://github.com/YosysHQ/yosys/issues/1482",
      "construct_complexity": 2,
      "ub_type": null,
      "error_pattern": "wrong_output"
    }
  ]
}
