{
  "tool": "verilator",
  "type": "issue",
  "issue_number": 5370,
  "issue_url": "https://github.com/verilator/verilator/issues/5370",
  "title": "Add type check to prevent C++ error: assigning to 'IData'  from incompatible type VlQueue",
  "body": "C++ errors:\r\n\r\n```\r\nclang++ -Os  -I.  -MMD -I.../tools/verilator/v5.026-g9c5c77c69/share/verilator/include -I.../tools/verilator/v5.026-g9c5c77c69/share/verilator/include/vltstd -DVM_COVERAGE=0 -DVM_SC=0 -DVM_TRACE=1 -DVM_TRACE_FST=0 -DVM_TRACE_VCD=1 -faligned-new -fcf-protection=none -Wno-bool-operation -Wno-shadow -Wno-sign-compare -Wno-tautological-compare -Wno-uninitialized -Wno-unused-but-set-parameter -Wno-unused-but-set-variable -Wno-unused-parameter -Wno-unused-variable  -Os  -DVM_SOLVER_DEFAULT='\"z3 --in\"' -std=c++14   -c -o Vtop__ALL.o Vtop__ALL.cpp\r\nIn file included from Vtop__ALL.cpp:5:\r\n./Vtop___024root__DepSet_h13c2fe66__0.cpp:111:23: error: assigning to 'IData' (aka 'unsigned int') from incompatible type 'VlQueue<IData>' (aka 'VlQueue<unsigned int>')\r\n  111 |                     = vlSelfRef.top__DOT__testbench__DOT__tile__DOT__mem_z_bfm__DOT__z_txn_qs\r\n      |                       ^~~~~~~~~~~~~~~~~~~~~~~~~~~~~~~~~~~~~~~~~~~~~~~~~~~~~~~~~~~~~~~~~~~~~~~\r\n  112 |                     [1U].find_index([&](IData/*31:0*/ item__DOT__index,\r\n      |                     ~~~~~~~~~~~~~~~~~~~~~~~~~~~~~~~~~~~~~~~~~~~~~~~~~~~\r\n  113 |                                         VlClassRef<Vtop___024unit__03a__03az_txn_class> item) {\r\n      |                                         ~~~~~~~~~~~~~~~~~~~~~~~~~~~~~~~~~~~~~~~~~~~~~~~~~~~~~~~\r\n  114 |                         return ((VL_NULL_CHECK(item, \"test.sv\", 106)\r\n      |                         ~~~~~~~~~~~~~~~~~~~~~~~~~~~~~~~~~~~~~~~~~~~~\r\n  115 |                                  ->__PVT__cid == VL_NULL_CHECK(\r\n      |                                  ~~~~~~~~~~~~~~~~~~~~~~~~~~~~~~\r\n  116 |                                                                vlSelfRef.top__DOT__testbench__DOT__tile__DOT__mem_z_bfm__DOT__z_txn\r\n      |                                                                ~~~~~~~~~~~~~~~~~~~~~~~~~~~~~~~~~~~~~~~~~~~~~~~~~~~~~~~~~~~~~~~~~~~~\r\n  117 |                                                                [1U], \"test.sv\", 106)\r\n      |                                                                ~~~~~~~~~~~~~~~~~~~~~\r\n  118 |                                  ->__PVT__cid));\r\n      |                                  ~~~~~~~~~~~~~~~\r\n  119 |                     }\r\n      |                     ~\r\n  120 |                 );\r\n      |                 ~\r\n./Vtop___024root__DepSet_h13c2fe66__0.cpp:179:23: error: assigning to 'IData' (aka 'unsigned int') from incompatible type 'VlQueue<IData>' (aka 'VlQueue<unsigned int>')\r\n  179 |                     = vlSelfRef.top__DOT__testbench__DOT__tile__DOT__mmio_z_bfm__DOT__z_txn_qs\r\n      |                       ^~~~~~~~~~~~~~~~~~~~~~~~~~~~~~~~~~~~~~~~~~~~~~~~~~~~~~~~~~~~~~~~~~~~~~~~\r\n  180 |                     [1U].find_index([&](IData/*31:0*/ item__DOT__index,\r\n      |                     ~~~~~~~~~~~~~~~~~~~~~~~~~~~~~~~~~~~~~~~~~~~~~~~~~~~\r\n  181 |                                         VlClassRef<Vtop___024unit__03a__03az_txn_class> item) {\r\n      |                                         ~~~~~~~~~~~~~~~~~~~~~~~~~~~~~~~~~~~~~~~~~~~~~~~~~~~~~~~\r\n  182 |                         return ((VL_NULL_CHECK(item, \"test.sv\", 106)\r\n      |                         ~~~~~~~~~~~~~~~~~~~~~~~~~~~~~~~~~~~~~~~~~~~~\r\n  183 |                                  ->__PVT__cid == VL_NULL_CHECK(\r\n      |                                  ~~~~~~~~~~~~~~~~~~~~~~~~~~~~~~\r\n  184 |                                                                vlSelfRef.top__DOT__testbench__DOT__tile__DOT__mmio_z_bfm__DOT__z_txn\r\n      |                                                                ~~~~~~~~~~~~~~~~~~~~~~~~~~~~~~~~~~~~~~~~~~~~~~~~~~~~~~~~~~~~~~~~~~~~~\r\n  185 |                                                                [1U], \"test.sv\", 106)\r\n      |                                                                ~~~~~~~~~~~~~~~~~~~~~\r\n  186 |                                  ->__PVT__cid));\r\n      |                                  ~~~~~~~~~~~~~~~\r\n  187 |                     }\r\n      |                     ~\r\n  188 |                 );\r\n      |                 ~\r\n2 errors generated.\r\n```\r\n\r\nVCS errors out:\r\n\r\n```\r\nError-[SV-IRTAV] Illegal reference to automatic variable\r\ntestbench.sv, 106\r\n\"z_bfm_sender.0.i\"\r\n  Hierarchical reference to automatic variable 'i' is not legal.\r\n  Declared at:\r\n  \"testbench.sv\", 95\r\n\r\n\r\nError-[SV-IRTAV] Illegal reference to automatic variable\r\ntestbench.sv, 106\r\n\"z_bfm_sender.0.i\"\r\n  Hierarchical reference to automatic variable 'i' is not legal.\r\n  Declared at:\r\n  \"testbench.sv\", 95\r\n\r\n\r\nError-[ICTA] Incompatible complex type\r\ntestbench.sv, 106\r\n  Incompatible complex type assignment\r\n  Type of source expression is incompatible with type of target expression. \r\n  Mismatching types cannot be used in assignments, initializations and \r\n  instantiations. The type of the target is 'int', while the type of the \r\n  source is 'int$[$]'.\r\n  Source Expression: z_txn_qs[z_bfm_sender.unnamed$$_0.i].find_index(item) \r\n  with ((item.cid == z_txn[z_bfm_sender.unnamed$$_0.i].cid))\r\n  \r\n\r\n3 errors\r\n```\r\n\r\nCan you attach an example that shows the issue?  (Must be openly licensed, ideally in test_regress format.)\r\n\r\n```\r\npackage z_pkg;\r\n   localparam int OPCODEW=3;\r\n   localparam int CIDW=4;\r\n   localparam int ADDRW=37;\r\n  typedef enum logic [OPCODEW-1:0] {\r\n    C   = 3'h 0,\r\n    D   = 3'h 1\r\n  } b_op_t;\r\n  typedef logic [CIDW-1:0]      cid_t;\r\n  typedef logic [ADDRW-1:0]     address_t;\r\n  typedef struct packed {\r\n    cid_t        cid;\r\n    b_op_t       opcode;\r\n    address_t    address;\r\n  } x2_ch_t;\r\n   typedef enum  {\r\n      CH_Y1,\r\n      CH_X2\r\n   } channel_t;\r\n   parameter channel_t CH_ALL[CH_X2+1] = '{CH_Y1, CH_X2};\r\n   typedef enum {\r\n      TXN_0,\r\n      TXN_1,\r\n      TXN_2,\r\n      TXN_3,\r\n      TXN_4,\r\n      TXN_5,\r\n      TXN_6,\r\n      TXN_7\r\n   } txn_type_t;\r\n   function txn_type_t txn_type(bit [2:0] opcode, channel_t ch);\r\n      case(opcode)\r\n        3'd0: begin\r\n           case(ch)\r\n             CH_X2: txn_type = TXN_7;\r\n             default:   txn_type = TXN_0;\r\n           endcase\r\n        end\r\n        3'd1: begin\r\n           case(ch)\r\n             CH_Y1: txn_type = TXN_3;\r\n             CH_X2: txn_type = TXN_4;\r\n             default:   txn_type = TXN_0;\r\n           endcase\r\n        end\r\n\tdefault: txn_type = TXN_0;\r\n      endcase  \r\n   endfunction  \r\nendpackage  \r\ninterface z_if;\r\n   import z_pkg::*;\r\n   logic         x2_valid;\r\n   x2_ch_t       x2;\r\n   function automatic logic x2_trig(); return x2_valid; endfunction\r\n   modport sender (\r\n      input  x2_valid,\r\n      input  x2,\r\n      import x2_trig\r\n   );\r\n   modport receiver (\r\n      output x2_valid,\r\n      output x2,\r\n      import x2_trig\r\n   );\r\nendinterface  \r\n   import z_pkg::*;\r\nclass z_txn_class;\r\n   rand txn_type_t   req_txn_type;\r\n   rand cid_t        cid;\r\n   rand address_t    address;\r\n   logic [2:0] \t     req_opcode;\r\n   static function z_txn_class generate_txn(txn_type_t _txn_type);\r\n      z_txn_class txn = new;\r\n      int success = txn.randomize() with {\r\n         req_txn_type == _txn_type;\r\n      };\r\n      assert(success != 0);\r\n      return txn;\r\n   endfunction  \r\nendclass\r\nmodule z_bfm_sender import z_pkg::*;\r\n  (\r\n   input  logic     clk,\r\n   input  logic     reset_l,\r\n   z_if.sender    z_if_sender\r\n   );\r\n   channel_t ch;  \r\n   typedef z_txn_class z_txn_q_t[$];\r\n   z_txn_q_t z_txn_qs[ch.num()];\r\n   z_txn_class z_txn[ch.num()];  \r\n   always @(posedge clk or negedge reset_l) begin\r\n      if (!reset_l) begin\r\n      end\r\n      else begin\r\n\t foreach (CH_ALL[i]) begin\r\n\t    case(CH_ALL[i])\r\n              CH_X2: begin\r\n\t\t if (z_if_sender.x2_trig()) begin\r\n\t\t    z_txn[i] = new;\r\n\t\t    z_txn[i].req_txn_type = txn_type(z_if_sender.x2.opcode, ch);\r\n\t\t    z_txn[i].cid          = z_if_sender.x2.cid;\r\n\t\t    z_txn[i].address      = z_if_sender.x2.address;\r\n\t\t    case(z_txn[i].req_txn_type)\r\n\t\t      TXN_3: begin\r\n\t\t\t z_txn_class txn_from_q;\r\n\t\t\t int idx = z_txn_qs[i].find_index with (item.cid == z_txn[i].cid);\r\n\t\t\t assert(idx >= 0);\r\n\t\t\t txn_from_q = z_txn_qs[i][idx];\r\n\t\t\t z_txn_qs[idx].delete(idx);\r\n\t\t      end\r\n\t\t      default: begin\r\n\t\t\t z_txn_qs[i].push_back(z_txn[i]);\r\n\t\t      end\r\n\t\t    endcase  \r\n\t\t end\r\n\t      end\r\n\t    endcase  \r\n\t end  \r\n      end  \r\n   end  \r\n   task start_txn(z_txn_class txn);\r\n      case(txn.req_txn_type)\r\n\tTXN_3: begin\r\n\t   z_txn_qs[CH_Y1].push_back(txn);\r\n\t   z_txn_qs[CH_X2].push_back(txn);\r\n\tend\r\n      endcase\r\n   endtask  \r\n   task automatic end_test(bit pass);\r\n      z_txn_class txn = z_txn_class::generate_txn(TXN_3);\r\n      txn.address = '1;\r\n      start_txn(txn);\r\n   endtask\r\nendmodule  \r\nmodule test_core_wrapper\r\n  (\r\n   input  logic     clk,\r\n   input  logic     reset_l,\r\n   z_if.sender    z,\r\n                    mmio_z\r\n   );\r\n   z_bfm_sender mem_z_bfm( .z_if_sender(z),\r\n\t\t\t       .* );\r\n   z_bfm_sender mmio_z_bfm( .z_if_sender(mmio_z),\r\n\t\t                .* );\r\n   integer cyc = 0;\r\n   always @ (posedge clk) begin\r\n      if (!reset_l) begin\r\n\t cyc <= 0;\r\n      end\r\n      else begin\r\n\t cyc <= cyc + 1;\r\n\t if (cyc == 10) begin\r\n\t    mmio_z_bfm.end_test(1);\r\n\t end\r\n      end\r\n   end  \r\nendmodule  \r\nmodule testbench_core_wrapper\r\n(\r\n input clk,\r\n input reset_l\r\n );\r\n   z_if         z(),\r\n                  mmio_z();\r\n   test_core_wrapper tile( .z     (z.sender),\r\n\t\t\t   .mmio_z(mmio_z.sender),\r\n\t\t\t   .* );\r\nendmodule\r\nmodule top\r\n  (\r\n   input bit clk /*verilator clocker*/ ,\r\n   input bit reset_l\r\n   );\r\n   testbench_core_wrapper testbench( .* );\r\nendmodule\r\n```\r\n\r\nWhat 'verilator' command line do we use to run your example?\r\n\r\n`verilator --cc --exe -sv --assert --trace --trace-params --trace-structs --report-unoptflat --no-timing --timescale 1ps/1ps --x-assign unique -CFLAGS '-std=c++14' --Mdir verilator_obj_dir --top-module top test.sv sim_main.cpp`\r\n\r\nWhat 'verilator --version' are you using?  Did you try it with the git master version?\r\n\r\n`Verilator 5.027 devel rev v5.026-134-g9c5c77c69`\r\n\r\nWhat OS and distribution are you using?\r\n\r\n`Linux 5.14.0-427.24.1.el9_4.x86_64`\r\n",
  "labels": [
    "area: lint",
    "status: ready"
  ],
  "state": "open",
  "created_at": "2024-08-14",
  "closed_at": null,
  "code_blocks": [],
  "linked_pr": null,
  "pr_files": null,
  "pr_test_files": null
}
