{
  "tool": "circt",
  "type": "pull_request",
  "issue_number": 6958,
  "issue_url": "https://github.com/llvm/circt/pull/6958",
  "title": "[LLHD] Replace entity with module",
  "body": "* use `!hw.inout` instead of `!llhd.sig` to make things work with `hw.module` (since inout types don't allow nested signals)\r\n* remove the `llhd.entity` operation and use the `hw.module` instead. This has two disadvantages: (1) all ports are now inout instead of separated in and out ports, however this was never verified in LLHD anyways and out ports were always more like inout, (2) instance and signal names cannot be verified to be unique within one module anymore\r\n* the HWToLLHD pass is removed because it only converted `hw.module` to `llhd.entity` and `hw.instance` to `llhd.inst`. We can potentially implement the ModuleLike interface for ProcOp and get rid of `llhd.inst` as well.\r\n* the function inlining pass does not work yet",
  "labels": [
    "LLHD"
  ],
  "state": "closed",
  "created_at": "2024-04-28",
  "closed_at": "2024-07-19",
  "code_blocks": [],
  "linked_pr": null,
  "pr_files": null,
  "pr_test_files": null
}
