{
  "tool": "yosys",
  "issue_number": 1688,
  "title": "$finish statement in always blocks produce errors",
  "features": [
    {
      "name": "$finish system task in always block",
      "category": "timing",
      "description": "Code should include a $finish system task used within an always block (not an initial block) for synthesizable RTL simulation assertions",
      "snippet": "always @(posedge clk) begin\n    if (simulation_error)\n        $finish;\nend",
      "tags": ["system_task", "finish", "always_block", "synthesis"],
      "source_bug_id": "1688",
      "tool": "yosys",
      "issue_url": "https://github.com/YosysHQ/yosys/issues/1688",
      "construct_complexity": 2,
      "ub_type": null,
      "error_pattern": "crash"
    },
    {
      "name": "$display system task in always block for comparison",
      "category": "timing",
      "description": "Code should include a $display system task used within an always block to demonstrate Yosys handles it as warning while $finish is treated as error",
      "snippet": "always @(*) begin\n    $display(\"state = %d\", state);\nend",
      "tags": ["system_task", "display", "always_block", "synthesis"],
      "source_bug_id": "1688",
      "tool": "yosys",
      "issue_url": "https://github.com/YosysHQ/yosys/issues/1688",
      "construct_complexity": 2,
      "ub_type": null,
      "error_pattern": null
    }
  ],
  "extraction_summary": {
    "code_blocks_found": 1,
    "features_extracted": 2,
    "features_after_dedup": 2
  }
}
